nonebot_plugin_whoasked/__init__.py
nonebot_plugin_whoasked/config.py
nonebot_plugin_whoasked/data_manager.py
nonebot_plugin_whoasked/log_filter.py
nonebot_plugin_whoasked-0.2.8.dist-info/LICENSE
nonebot_plugin_whoasked-0.2.8.dist-info/METADATA
nonebot_plugin_whoasked-0.2.8.dist-info/WHEEL
nonebot_plugin_whoasked-0.2.8.dist-info/RECORD
