Metadata-Version: 2.3
Name: nonebot-plugin-whoasked
Version: 0.2.8
Summary: 查询谁@了你或引用了你的消息
License: MIT
Author: enKl03B
Author-email: enkl03b@163.com
Requires-Python: >=3.9,<4.0
Classifier: License :: OSI Approved :: MIT License
Classifier: Programming Language :: Python :: 3
Classifier: Programming Language :: Python :: 3.9
Classifier: Programming Language :: Python :: 3.10
Classifier: Programming Language :: Python :: 3.11
Classifier: Programming Language :: Python :: 3.12
Classifier: Programming Language :: Python :: 3.13
Requires-Dist: nonebot-adapter-onebot (>=2.0.0)
Requires-Dist: nonebot-plugin-localstore (>=0.7.0)
Requires-Dist: nonebot2 (>=2.4.2)
Requires-Dist: pydantic (>=1.10.0)
Project-URL: Homepage, https://github.com/enKl03B/nonebot-plugin-whoasked
